client/__init__.py
client/add_contact.py
client/database.py
client/del_contact.py
client/main_window.py
client/main_window_conv.py
client/start_dialog.py
client/transport.py
PyQt_message_client-0.0.1.dist-info/METADATA
PyQt_message_client-0.0.1.dist-info/WHEEL
PyQt_message_client-0.0.1.dist-info/top_level.txt
PyQt_message_client-0.0.1.dist-info/RECORD
